pytradfri/VERSION
pytradfri/__init__.py
pytradfri/__main__.py
pytradfri/color.py
pytradfri/command.py
pytradfri/const.py
pytradfri/error.py
pytradfri/gateway.py
pytradfri/group.py
pytradfri/mood.py
pytradfri/py.typed
pytradfri/resource.py
pytradfri/smart_task.py
pytradfri/util.py
pytradfri/api/__init__.py
pytradfri/api/aiocoap_api.py
pytradfri/api/libcoap_api.py
pytradfri/device/__init__.py
pytradfri/device/air_purifier.py
pytradfri/device/air_purifier_control.py
pytradfri/device/base_controller.py
pytradfri/device/blind.py
pytradfri/device/blind_control.py
pytradfri/device/light.py
pytradfri/device/light_control.py
pytradfri/device/signal_repeater.py
pytradfri/device/signal_repeater_control.py
pytradfri/device/socket.py
pytradfri/device/socket_control.py
pytradfri-13.0.0.dist-info/LICENSE
pytradfri-13.0.0.dist-info/METADATA
pytradfri-13.0.0.dist-info/WHEEL
pytradfri-13.0.0.dist-info/top_level.txt
pytradfri-13.0.0.dist-info/RECORD
