Metadata-Version: 2.1
Name: pytradfri
Version: 13.0.0
Summary: IKEA Trådfri/Tradfri API. Control and observe your lights from Python.
Home-page: https://github.com/home-assistant-libs/pytradfri
Download-URL: https://github.com/home-assistant-libs/pytradfri/archive/13.0.0.zip
Author: balloob, lwis, ggravlingen, janiversen
Author-email: no@email.com
License: MIT
Keywords: ikea tradfri api iot light homeautomation
Classifier: Development Status :: 5 - Production/Stable
Classifier: Intended Audience :: Developers
Classifier: Natural Language :: English
Classifier: Programming Language :: Python :: 3
Classifier: Programming Language :: Python :: 3.10
Classifier: Programming Language :: Python :: 3.11
Classifier: Topic :: Home Automation
Requires-Python: >=3.10
License-File: LICENSE
Requires-Dist: pydantic
Provides-Extra: async
Requires-Dist: aiocoap (~=0.4.5) ; extra == 'async'
Requires-Dist: DTLSSocket (~=0.1.12) ; extra == 'async'
